Metadata-Version: 2.4
Name: applephrase
Version: 1.0.2
Summary: Generate memorable passphrases using pseudowords.
Author: Brent Huisman
Author-email: brent@huisman.pl
Maintainer-email: Brent Huisman <brent@huisman.pl>
Project-URL: homepage, https://github.com/brenthuisman/applephrase
Project-URL: documentation, https://github.com/brenthuisman/applephrase
Project-URL: repository, https://github.com/brenthuisman/applephrase
Project-URL: changelog, https://github.com/brenthuisman/applephrase/blob/master/README.md
Keywords: passphrase,password,pseudoword,gibberish
Classifier: Development Status :: 5 - Production/Stable
Classifier: License :: OSI Approved :: MIT License
Classifier: Programming Language :: Python :: 3
Classifier: Environment :: Console
Classifier: Topic :: Utilities
Classifier: Operating System :: OS Independent
Requires-Python: >=3.8
License-File: LICENSE
Requires-Dist: Levenshtein
Requires-Dist: statsmodels
Dynamic: license-file
